pygenie/__init__.py
pygenie/auth.py
pygenie/client.py
pygenie/conf.py
pygenie/exceptions.py
pygenie/genie.ini
pygenie/utils.py
pygenie/adapter/__init__.py
pygenie/adapter/adapter.py
pygenie/adapter/genie_2.py
pygenie/adapter/genie_3.py
pygenie/adapter/genie_x.py
pygenie/jobs/__init__.py
pygenie/jobs/core.py
pygenie/jobs/hadoop.py
pygenie/jobs/hive.py
pygenie/jobs/pig.py
pygenie/jobs/presto.py
pygenie/jobs/running.py
pygenie/jobs/sqoop.py
pygenie/jobs/utils.py
nflx_genie_client-3.6.19.dist-info/LICENSE.txt
nflx_genie_client-3.6.19.dist-info/METADATA
nflx_genie_client-3.6.19.dist-info/WHEEL
nflx_genie_client-3.6.19.dist-info/top_level.txt
nflx_genie_client-3.6.19.dist-info/RECORD
