Metadata-Version: 2.2
Name: nflx-genie-client
Version: 3.6.19
Summary: Genie Python Client.
Home-page: http://netflix.github.io/genie/
Author: Netflix Inc.
Author-email: genieoss@googlegroups.com
License: Apache 2.0
Keywords: genie hadoop cloud netflix client bigdata presto
Classifier: Development Status :: 5 - Production/Stable
Classifier: Intended Audience :: Developers
Classifier: Intended Audience :: Science/Research
Classifier: Intended Audience :: System Administrators
Classifier: Topic :: Scientific/Engineering
Classifier: Topic :: Software Development :: Libraries
Classifier: Topic :: Software Development :: Libraries :: Python Modules
Classifier: Topic :: System :: Distributed Computing
Classifier: Topic :: Utilities
Classifier: License :: OSI Approved :: Apache Software License
Classifier: Programming Language :: Python
Classifier: Programming Language :: Python :: 3.9
Classifier: Programming Language :: Python :: 3.10
License-File: LICENSE.txt
Requires-Dist: decorator
Requires-Dist: multipledispatch
Requires-Dist: pyconfigurator
Requires-Dist: python-dateutil>=2.4
Requires-Dist: requests
Requires-Dist: six
Requires-Dist: importlib-metadata
Dynamic: author
Dynamic: author-email
Dynamic: classifier
Dynamic: description
Dynamic: description-content-type
Dynamic: home-page
Dynamic: keywords
Dynamic: license
Dynamic: requires-dist
Dynamic: summary
